[{"id":1,"type":"task_created","description":"James Rivera created task \"Write test cases for login module\"","user_id":3,"entity_id":1,"entity_type":"task","created_at":"2026-05-13T03:30:20.701Z"},{"id":2,"type":"test_case_created","description":"Priya Patel created test case \"Checkout with valid card\" (AI-assisted)","user_id":4,"entity_id":5,"entity_type":"test_case","created_at":"2026-05-13T03:30:20.701Z"},{"id":3,"type":"task_status_changed","description":"Sarah Chen moved \"Execute regression suite\" to In Progress","user_id":2,"entity_id":2,"entity_type":"task","created_at":"2026-05-13T03:30:20.701Z"},{"id":4,"type":"requirement_created","description":"Admin User created requirement \"Push Notification Support\"","user_id":1,"entity_id":3,"entity_type":"requirement","created_at":"2026-05-13T03:30:20.701Z"},{"id":5,"type":"test_case_created","description":"Marcus Kim created test case \"Dashboard mobile layout\"","user_id":5,"entity_id":6,"entity_type":"test_case","created_at":"2026-05-13T03:30:20.701Z"},{"id":6,"type":"task_status_changed","description":"James Rivera completed \"Test push notification delivery\"","user_id":3,"entity_id":8,"entity_type":"task","created_at":"2026-05-13T03:30:20.701Z"},{"id":7,"type":"requirement_created","description":"Requirement \"Password testing on login page\" was created","user_id":null,"entity_id":9,"entity_type":"requirement","created_at":"2026-05-14T06:45:22.581Z"},{"id":8,"type":"test_case_created","description":"Test case \"Password meets all complexity rules and allows login\" was created (AI-assisted)","user_id":null,"entity_id":9,"entity_type":"test_case","created_at":"2026-05-14T06:47:10.116Z"},{"id":9,"type":"test_case_created","description":"Test case \"Password longer than 12 characters with all required character types\" was created (AI-assisted)","user_id":null,"entity_id":12,"entity_type":"test_case","created_at":"2026-05-14T06:47:10.118Z"},{"id":10,"type":"test_case_created","description":"Test case \"Password exactly 12 characters with all required character types\" was created (AI-assisted)","user_id":null,"entity_id":10,"entity_type":"test_case","created_at":"2026-05-14T06:47:10.118Z"},{"id":11,"type":"test_case_created","description":"Test case \"Password with multiple symbols meets complexity and allows login\" was created (AI-assisted)","user_id":null,"entity_id":11,"entity_type":"test_case","created_at":"2026-05-14T06:47:10.119Z"},{"id":12,"type":"test_case_created","description":"Test case \"Password validation message for too-short password\" was created (AI-assisted)","user_id":null,"entity_id":13,"entity_type":"test_case","created_at":"2026-05-14T06:47:10.202Z"},{"id":13,"type":"test_case_created","description":"Test case \"Password missing uppercase letter is rejected\" was created (AI-assisted)","user_id":null,"entity_id":14,"entity_type":"test_case","created_at":"2026-05-14T06:47:10.204Z"},{"id":14,"type":"test_case_created","description":"Test case \"Password missing lowercase letter is rejected\" was created (AI-assisted)","user_id":null,"entity_id":15,"entity_type":"test_case","created_at":"2026-05-14T06:47:10.209Z"},{"id":15,"type":"test_case_created","description":"Test case \"Password missing number is rejected\" was created (AI-assisted)","user_id":null,"entity_id":16,"entity_type":"test_case","created_at":"2026-05-14T06:47:10.211Z"},{"id":16,"type":"test_case_created","description":"Test case \"Password missing symbol is rejected\" was created (AI-assisted)","user_id":null,"entity_id":17,"entity_type":"test_case","created_at":"2026-05-14T06:47:10.285Z"},{"id":17,"type":"test_case_created","description":"Test case \"Password containing first name is rejected\" was created (AI-assisted)","user_id":null,"entity_id":18,"entity_type":"test_case","created_at":"2026-05-14T06:47:10.292Z"},{"id":18,"type":"test_case_created","description":"Test case \"Password containing last name is rejected\" was created (AI-assisted)","user_id":null,"entity_id":19,"entity_type":"test_case","created_at":"2026-05-14T06:47:10.299Z"},{"id":19,"type":"test_case_created","description":"Test case \"Password containing partial name fragment is rejected\" was created (AI-assisted)","user_id":null,"entity_id":20,"entity_type":"test_case","created_at":"2026-05-14T06:47:10.301Z"},{"id":20,"type":"test_case_created","description":"Test case \"Password with allowed special characters only is accepted\" was created (AI-assisted)","user_id":null,"entity_id":21,"entity_type":"test_case","created_at":"2026-05-14T06:47:10.314Z"},{"id":21,"type":"test_case_created","description":"Test case \"Password with disallowed special character is rejected\" was created (AI-assisted)","user_id":null,"entity_id":22,"entity_type":"test_case","created_at":"2026-05-14T06:47:10.326Z"},{"id":22,"type":"test_case_created","description":"Test case \"Password complexity error shown before authentication attempt\" was created (AI-assisted)","user_id":null,"entity_id":23,"entity_type":"test_case","created_at":"2026-05-14T06:47:10.368Z"},{"id":23,"type":"test_case_created","description":"Test case \"Multiple password complexity violations are reported clearly\" was created (AI-assisted)","user_id":null,"entity_id":24,"entity_type":"test_case","created_at":"2026-05-14T06:47:10.378Z"},{"id":24,"type":"test_case_created","description":"Test case \"Password with correct complexity but wrong value shows invalid credentials\" was created (AI-assisted)","user_id":null,"entity_id":25,"entity_type":"test_case","created_at":"2026-05-14T06:47:10.388Z"},{"id":25,"type":"task_released","description":"Task \"Verify payment gateway integration\" was released and is now available for pick-up","user_id":4,"entity_id":3,"entity_type":"task","created_at":"2026-05-14T07:14:48.509Z"},{"id":26,"type":"task_assigned","description":"Task \"Verify payment gateway integration\" was assigned","user_id":3,"entity_id":3,"entity_type":"task","created_at":"2026-05-14T07:14:56.575Z"},{"id":27,"type":"requirement_created","description":"Requirement \"Contact Number\" was created","user_id":null,"entity_id":10,"entity_type":"requirement","created_at":"2026-05-14T07:44:31.530Z"},{"id":28,"type":"test_case_created","description":"Test case \"Create contact number with valid minimum length\" was created (AI-assisted)","user_id":null,"entity_id":26,"entity_type":"test_case","created_at":"2026-05-14T07:46:56.560Z"},{"id":29,"type":"test_case_created","description":"Test case \"Create contact number with non-zero first digit after country code\" was created (AI-assisted)","user_id":null,"entity_id":27,"entity_type":"test_case","created_at":"2026-05-14T07:46:56.564Z"},{"id":30,"type":"test_case_created","description":"Test case \"Create contact number with valid maximum length\" was created (AI-assisted)","user_id":null,"entity_id":29,"entity_type":"test_case","created_at":"2026-05-14T07:46:56.564Z"},{"id":31,"type":"test_case_created","description":"Test case \"Create contact number with typical valid length\" was created (AI-assisted)","user_id":null,"entity_id":28,"entity_type":"test_case","created_at":"2026-05-14T07:46:56.565Z"},{"id":32,"type":"test_case_created","description":"Test case \"Create contact number with numeric characters only\" was created (AI-assisted)","user_id":null,"entity_id":30,"entity_type":"test_case","created_at":"2026-05-14T07:46:56.646Z"},{"id":33,"type":"test_case_created","description":"Test case \"Create contact number with different valid country codes\" was created (AI-assisted)","user_id":null,"entity_id":31,"entity_type":"test_case","created_at":"2026-05-14T07:46:56.660Z"},{"id":34,"type":"test_case_created","description":"Test case \"Create unique contact number not used before\" was created (AI-assisted)","user_id":null,"entity_id":32,"entity_type":"test_case","created_at":"2026-05-14T07:46:56.662Z"},{"id":35,"type":"test_case_created","description":"Test case \"Reject contact number shorter than minimum length\" was created (AI-assisted)","user_id":null,"entity_id":33,"entity_type":"test_case","created_at":"2026-05-14T07:46:56.662Z"},{"id":36,"type":"test_case_created","description":"Test case \"Reject contact number longer than maximum length\" was created (AI-assisted)","user_id":null,"entity_id":34,"entity_type":"test_case","created_at":"2026-05-14T07:46:56.733Z"},{"id":37,"type":"test_case_created","description":"Test case \"Reject contact number starting with zero after country code\" was created (AI-assisted)","user_id":null,"entity_id":35,"entity_type":"test_case","created_at":"2026-05-14T07:46:56.749Z"},{"id":38,"type":"test_case_created","description":"Test case \"Reject contact number containing symbols\" was created (AI-assisted)","user_id":null,"entity_id":36,"entity_type":"test_case","created_at":"2026-05-14T07:46:56.752Z"},{"id":39,"type":"test_case_created","description":"Test case \"Reject contact number containing plus sign in local part\" was created (AI-assisted)","user_id":null,"entity_id":37,"entity_type":"test_case","created_at":"2026-05-14T07:46:56.755Z"},{"id":40,"type":"test_case_created","description":"Test case \"Reject contact number containing alphabetic characters\" was created (AI-assisted)","user_id":null,"entity_id":38,"entity_type":"test_case","created_at":"2026-05-14T07:46:56.796Z"},{"id":41,"type":"test_case_created","description":"Test case \"Reject existing contact number already stored\" was created (AI-assisted)","user_id":null,"entity_id":39,"entity_type":"test_case","created_at":"2026-05-14T07:46:56.797Z"},{"id":42,"type":"test_case_created","description":"Test case \"Reject contact number field left empty\" was created (AI-assisted)","user_id":null,"entity_id":40,"entity_type":"test_case","created_at":"2026-05-14T07:46:56.823Z"},{"id":43,"type":"test_case_created","description":"Test case \"Reject contact number with leading and trailing spaces\" was created (AI-assisted)","user_id":null,"entity_id":41,"entity_type":"test_case","created_at":"2026-05-14T07:46:56.840Z"},{"id":44,"type":"test_case_created","description":"Test case \"Reject contact number with internal spaces\" was created (AI-assisted)","user_id":null,"entity_id":42,"entity_type":"test_case","created_at":"2026-05-14T07:46:56.844Z"},{"id":45,"type":"test_case_created","description":"Test case \"Reject contact number containing punctuation symbols\" was created (AI-assisted)","user_id":null,"entity_id":43,"entity_type":"test_case","created_at":"2026-05-14T07:46:56.849Z"},{"id":46,"type":"test_case_created","description":"Test case \"Reject contact number with mixed digits and special characters\" was created (AI-assisted)","user_id":null,"entity_id":44,"entity_type":"test_case","created_at":"2026-05-14T07:46:57.082Z"},{"id":47,"type":"test_case_created","description":"Test case \"Reject contact number with leading zero and no explicit country code\" was created (AI-assisted)","user_id":null,"entity_id":45,"entity_type":"test_case","created_at":"2026-05-14T07:46:57.084Z"},{"id":48,"type":"requirement_created","description":"Requirement \"asdasd\" was created","user_id":null,"entity_id":11,"entity_type":"requirement","created_at":"2026-05-14T14:15:45.560Z"},{"id":49,"type":"requirement_created","description":"Requirement \"Login username now need to use email only\" was created","user_id":null,"entity_id":12,"entity_type":"requirement","created_at":"2026-05-15T03:47:27.899Z"},{"id":50,"type":"test_case_created","description":"Test case \"Test: Login username now need to use email only\" was created (AI-assisted)","user_id":null,"entity_id":46,"entity_type":"test_case","created_at":"2026-05-15T03:49:16.102Z"}]