[{"id":1,"title":"UAT Sprint 3","description":"Full UAT for sprint 3","date":"2026-05-20","event_type":"uat","tagged_user_ids":"[2,3]","color":null,"created_by":1,"created_at":"2026-05-14T07:14:28.175Z","updated_at":"2026-05-14T07:14:28.175Z"},{"id":2,"title":"UAT Sprint 3","description":"Full UAT for sprint 3","date":"2026-05-20","event_type":"uat","tagged_user_ids":"[2,3]","color":null,"created_by":1,"created_at":"2026-05-14T07:14:34.564Z","updated_at":"2026-05-14T07:14:34.564Z"},{"id":3,"title":"Sprint Planning","description":null,"date":"2026-05-16","event_type":"meeting","tagged_user_ids":"[2,3,4,5]","color":null,"created_by":2,"created_at":"2026-05-14T07:14:47.419Z","updated_at":"2026-05-14T07:14:47.419Z"},{"id":4,"title":"Release v3.0","description":"Mobile App v3.0 production release","date":"2026-05-28","event_type":"release","tagged_user_ids":"[1,2]","color":null,"created_by":1,"created_at":"2026-05-14T07:14:47.462Z","updated_at":"2026-05-14T07:14:47.462Z"},{"id":5,"title":"Payment fix deadline","description":null,"date":"2026-05-14","event_type":"deadline","tagged_user_ids":"[4]","color":null,"created_by":1,"created_at":"2026-05-14T07:14:47.504Z","updated_at":"2026-05-14T07:14:47.504Z"},{"id":6,"title":"QA Retrospective","description":null,"date":"2026-05-22","event_type":"meeting","tagged_user_ids":"[2,3,4,5]","color":null,"created_by":2,"created_at":"2026-05-14T07:14:47.546Z","updated_at":"2026-05-14T07:14:47.546Z"},{"id":7,"title":"QA Outing","description":"QA OUTING at Sungai Semungkis, Hulu Langat, Selangor.","date":"2026-10-31","event_type":"other","tagged_user_ids":"[1,13,9,15,3,14,5,4,8,10,6,2,7,12,11]","color":null,"created_by":2,"created_at":"2026-05-18T02:45:56.223Z","updated_at":"2026-05-18T02:45:56.223Z"}]